optimech/__init__.py
optimech/body3d/__init__.py
optimech/body3d/analysis.py
optimech/body3d/io.py
optimech/body3d/tracking.py
optimech/body3d/video.py
optimech/body3d/vision.py
optimech/body3d/visualization.py
optimech/tensile/__init__.py
optimech/tensile/analysis.py
optimech/tensile/io.py
optimech/tensile/tracking.py
optimech/tensile/video.py
optimech/tensile/vision.py
optimech/tensile/visualization.py
optimech-0.1.2.dist-info/licenses/LICENSE
optimech-0.1.2.dist-info/METADATA
optimech-0.1.2.dist-info/WHEEL
optimech-0.1.2.dist-info/top_level.txt
optimech-0.1.2.dist-info/RECORD
