Metadata-Version: 2.4
Name: optimech
Version: 0.1.2
Summary: Video-based analysis tools for tensile tests and 3D-printed body displacement
Author-email: Amaia Marin <amaia.marin@alumni.mondragon.edu>
License-Expression: MIT
Project-URL: Homepage, https://github.com/amaiamarinn/optimech
Keywords: displacement,strain,video-analysis
Classifier: Programming Language :: Python :: 3
Classifier: Operating System :: OS Independent
Requires-Python: >=3.9
License-File: LICENSE
Requires-Dist: numpy
Requires-Dist: opencv-python
Requires-Dist: matplotlib
Requires-Dist: plotly
Requires-Dist: pandas
Requires-Dist: imageio
Dynamic: license-file
